pai_browser_use/__init__.py
pai_browser_use/_config.py
pai_browser_use/_image_utils.py
pai_browser_use/_logger.py
pai_browser_use/_session.py
pai_browser_use/_tools.py
pai_browser_use/toolset.py
pai_browser_use/tools/__init__.py
pai_browser_use/tools/_types.py
pai_browser_use/tools/dialog.py
pai_browser_use/tools/form.py
pai_browser_use/tools/interaction.py
pai_browser_use/tools/navigation.py
pai_browser_use/tools/query.py
pai_browser_use/tools/state.py
pai_browser_use/tools/validation.py
pai_browser_use/tools/wait.py
pai_browser_use-0.3.0.dist-info/METADATA
pai_browser_use-0.3.0.dist-info/WHEEL
pai_browser_use-0.3.0.dist-info/licenses/LICENSE
pai_browser_use-0.3.0.dist-info/RECORD
