Metadata-Version: 2.4
Name: pai-browser-use
Version: 0.3.0
Summary: Pydantic AI Toolsets for browser use
Project-URL: Homepage, https://wh1isper.github.io/pai-browser-use/
Project-URL: Repository, https://github.com/wh1isper/pai-browser-use
Project-URL: Documentation, https://wh1isper.github.io/pai-browser-use/
Author-email: Wh1isper <jizhongsheng957@gmail.com>
License-File: LICENSE
Keywords: agent,ai,automation,browser,browser-use,cdp,llm,pydantic,pydantic-ai,python,scraping
Classifier: Intended Audience :: Developers
Classifier: Programming Language :: Python
Classifier: Programming Language :: Python :: 3
Classifier: Programming Language :: Python :: 3.11
Classifier: Programming Language :: Python :: 3.12
Classifier: Programming Language :: Python :: 3.13
Classifier: Topic :: Software Development :: Libraries :: Python Modules
Requires-Python: <4.0,>=3.11
Requires-Dist: cdp-use<2.0.0,>=1.4.1
Requires-Dist: httpx>=0.28.1
Requires-Dist: pillow>=11.3.0
Requires-Dist: pydantic-ai<2.0.0,>=1.0.10
Requires-Dist: pydantic-settings>=2.10.1
Requires-Dist: pydantic>=2.11.9
Requires-Dist: python-dotenv>=1.1.1
Requires-Dist: typing-extensions>=4.15.0
